CHANGES.rst
LICENSE.txt
MANIFEST.in
README.rst
TODO.rst
setup.cfg
setup.py
docs/Makefile
docs/api.rst
docs/architecture.rst
docs/changes.rst
docs/conf.py
docs/glossary.rst
docs/index.rst
docs/make.bat
docs/providers.rst
docs/usage.rst
docs/_build/doctrees/api.doctree
docs/_build/doctrees/architecture.doctree
docs/_build/doctrees/changes.doctree
docs/_build/doctrees/environment.pickle
docs/_build/doctrees/glossary.doctree
docs/_build/doctrees/index.doctree
docs/_build/doctrees/providers.doctree
docs/_build/doctrees/usage.doctree
docs/_build/doctrees/api/app.doctree
docs/_build/doctrees/api/toplevel.doctree
docs/_build/doctrees/api/utils.doctree
docs/_build/doctrees/providers/facebook.doctree
docs/_build/doctrees/providers/github.doctree
docs/_build/doctrees/providers/google.doctree
docs/_build/doctrees/providers/google_hybrid.doctree
docs/_build/doctrees/providers/google_oauth2.doctree
docs/_build/doctrees/providers/live.doctree
docs/_build/doctrees/providers/mailru.doctree
docs/_build/doctrees/providers/openid.doctree
docs/_build/doctrees/providers/twitter.doctree
docs/_build/doctrees/providers/vk.doctree
docs/_build/doctrees/providers/yahoo.doctree
docs/_build/doctrees/providers/yandex.doctree
docs/_build/html/.buildinfo
docs/_build/html/api.html
docs/_build/html/architecture.html
docs/_build/html/changes.html
docs/_build/html/genindex.html
docs/_build/html/glossary.html
docs/_build/html/index.html
docs/_build/html/objects.inv
docs/_build/html/providers.html
docs/_build/html/py-modindex.html
docs/_build/html/search.html
docs/_build/html/searchindex.js
docs/_build/html/usage.html
docs/_build/html/_images/overview.png
docs/_build/html/_modules/index.html
docs/_build/html/_modules/velruse.html
docs/_build/html/_modules/velruse/app.html
docs/_build/html/_modules/velruse/utils.html
docs/_build/html/_modules/velruse/providers/facebook.html
docs/_build/html/_modules/velruse/providers/github.html
docs/_build/html/_modules/velruse/providers/google_hybrid.html
velruse.egg-info/PKG-INFO
velruse.egg-info/SOURCES.txt
velruse.egg-info/dependency_links.txt
velruse.egg-info/entry_points.txt
velruse.egg-info/not-zip-safe
velruse.egg-info/requires.txt
velruse.egg-info/top_level.txt
